{
  "categories": [
    {
      "categoryName": "Kategori 1",
      "categoryIcon": "icon1.png",
      "categoryColor": "FF5733",
      "categoryDices": [
        {
          "dice_name": "Kahve",
          "icon": "assets/icon",
          "id": "1",
          "isPremium": false,
          "isAdultContent": false,
          "description": "",
          "sub_dices": [
            {"name": "Kahve", "options": [{"id": "1", "name": "a"}, {"id": "2", "name": "b"}, {"id": "3", "name": "c"}, {"id": "4", "name": "d"}, {"id": "5", "name": "e"}, {"id": "6", "name": "f"}]}
          ]
        },
        {
          "dice_name": "Çay",
          "icon": "assets/icon",
          "id": "2",
          "isPremium": true,
          "isAdultContent": false,
          "description": "",
          "sub_dices": [
            {"name": "Çay", "options": [{"id": "1", "name": "a"}, {"id": "2", "name": "b"}, {"id": "3", "name": "c"}, {"id": "4", "name": "d"}, {"id": "5", "name": "e"}, {"id": "6", "name": "f"}]}
          ]
        }
      ]
    },
    {
      "categoryName": "Kategori 2",
      "categoryIcon": "icon2.png",
      "categoryColor": "3366FF",
      "categoryDices": [
        {
          "dice_name": "Meyve Suyu",
          "icon": "assets/icon",
          "id": "3",
          "isPremium": false,
          "isAdultContent": true,
          "description": "",
          "sub_dices": [
            {"name": "Meyve Suyu", "options": [{"id": "1", "name": "a"}, {"id": "2", "name": "b"}, {"id": "3", "name": "c"}, {"id": "4", "name": "d"}, {"id": "5", "name": "e"}, {"id": "6", "name": "f"}]}
          ]
        }
      ]
    }
  ]
}